mcpdoc/__init__.py
mcpdoc/_version.py
mcpdoc/cli.py
mcpdoc/langgraph.py
mcpdoc/main.py
mcpdoc/splash.py
iflow_mcp_mcpdoc_server-0.0.11.dist-info/METADATA
iflow_mcp_mcpdoc_server-0.0.11.dist-info/WHEEL
iflow_mcp_mcpdoc_server-0.0.11.dist-info/entry_points.txt
iflow_mcp_mcpdoc_server-0.0.11.dist-info/licenses/LICENSE
iflow_mcp_mcpdoc_server-0.0.11.dist-info/RECORD
